airfeedback/__init__.py
airfeedback/main.py
airfeedback-0.1.1.dist-info/WHEEL
airfeedback-0.1.1.dist-info/METADATA
airfeedback-0.1.1.dist-info/RECORD
