Metadata-Version: 2.3
Name: airfeedback
Version: 0.1.1
Summary: Simple feedback collection for Air/FastAPI apps
Author: Isaac Flath
Author-email: Isaac Flath <isaac@kentro.tech>
Requires-Dist: air>=0.40.0
Requires-Dist: fastapi[standard]>=0.121.1
Requires-Python: >=3.13
Project-URL: Homepage, https://github.com/kentro-tech/airfeedback
Project-URL: Issues, https://github.com/kentro-tech/airfeedback/issues
